[
  {
    "title": "alibaba/fastjson2",
    "url": "https://github.com/alibaba/fastjson2",
    "lang": "Java"
  },
  {
    "title": "projectdiscovery/nuclei-templates",
    "url": "https://github.com/projectdiscovery/nuclei-templates",
    "lang": "Python"
  },
  {
    "title": "dair-ai/ML-Course-Notes",
    "url": "https://github.com/dair-ai/ML-Course-Notes"
  },
  {
    "title": "DataTalksClub/mlops-zoomcamp",
    "url": "https://github.com/DataTalksClub/mlops-zoomcamp",
    "lang": "JupyterNotebook"
  },
  {
    "title": "NebuTech/NBMiner",
    "url": "https://github.com/NebuTech/NBMiner"
  },
  {
    "title": "microsoft/Web-Dev-For-Beginners",
    "url": "https://github.com/microsoft/Web-Dev-For-Beginners",
    "lang": "JavaScript"
  },
  {
    "title": "naptha/tesseract.js",
    "url": "https://github.com/naptha/tesseract.js",
    "lang": "JavaScript"
  },
  {
    "title": "docker/awesome-compose",
    "url": "https://github.com/docker/awesome-compose",
    "lang": "HTML"
  },
  {
    "title": "HIT-UG-Group/DeepLearning-MuLi-Notes",
    "url": "https://github.com/HIT-UG-Group/DeepLearning-MuLi-Notes",
    "lang": "JupyterNotebook"
  },
  {
    "title": "pojntfx/weron",
    "url": "https://github.com/pojntfx/weron",
    "lang": "Go"
  },
  {
    "title": "Vonng/ddia",
    "url": "https://github.com/Vonng/ddia",
    "lang": "Python"
  },
  {
    "title": "tauri-apps/tauri",
    "url": "https://github.com/tauri-apps/tauri",
    "lang": "Rust"
  },
  {
    "title": "digitalocean/nginxconfig.io",
    "url": "https://github.com/digitalocean/nginxconfig.io",
    "lang": "JavaScript"
  },
  {
    "title": "go-kratos/kratos",
    "url": "https://github.com/go-kratos/kratos",
    "lang": "Go"
  },
  {
    "title": "MoienTajik/AspNetCore-Developer-Roadmap",
    "url": "https://github.com/MoienTajik/AspNetCore-Developer-Roadmap"
  },
  {
    "title": "alexeygrigorev/mlbookcamp-code",
    "url": "https://github.com/alexeygrigorev/mlbookcamp-code",
    "lang": "JupyterNotebook"
  },
  {
    "title": "MichaelCade/90DaysOfDevOps",
    "url": "https://github.com/MichaelCade/90DaysOfDevOps",
    "lang": "Shell"
  },
  {
    "title": "meysamhadeli/booking-microservices-sample",
    "url": "https://github.com/meysamhadeli/booking-microservices-sample",
    "lang": "C#"
  },
  {
    "title": "paulgp/applied-methods-phd",
    "url": "https://github.com/paulgp/applied-methods-phd",
    "lang": "TeX"
  },
  {
    "title": "Jdsleppy/django-orm-cheatsheet",
    "url": "https://github.com/Jdsleppy/django-orm-cheatsheet"
  },
  {
    "title": "gogs/gogs",
    "url": "https://github.com/gogs/gogs",
    "lang": "Go"
  },
  {
    "title": "google/googletest",
    "url": "https://github.com/google/googletest",
    "lang": "C++"
  },
  {
    "title": "kubesphere/kubesphere",
    "url": "https://github.com/kubesphere/kubesphere",
    "lang": "Go"
  },
  {
    "title": "BabylonJS/Babylon.js",
    "url": "https://github.com/BabylonJS/Babylon.js",
    "lang": "TypeScript"
  },
  {
    "title": "Tencent/tmagic-editor",
    "url": "https://github.com/Tencent/tmagic-editor",
    "lang": "TypeScript"
  }
]