[
  {
    "title": "TGX-Android/Telegram-X",
    "url": "https://github.com/TGX-Android/Telegram-X",
    "lang": "Java"
  },
  {
    "title": "elebumm/RedditVideoMakerBot",
    "url": "https://github.com/elebumm/RedditVideoMakerBot",
    "lang": "Python"
  },
  {
    "title": "ToolJet/ToolJet",
    "url": "https://github.com/ToolJet/ToolJet",
    "lang": "JavaScript"
  },
  {
    "title": "spacedriveapp/spacedrive",
    "url": "https://github.com/spacedriveapp/spacedrive",
    "lang": "TypeScript"
  },
  {
    "title": "open-goal/jak-project",
    "url": "https://github.com/open-goal/jak-project",
    "lang": "CommonLisp"
  },
  {
    "title": "revanced/revanced-patches",
    "url": "https://github.com/revanced/revanced-patches",
    "lang": "Kotlin"
  },
  {
    "title": "Anduin2017/HowToCook",
    "url": "https://github.com/Anduin2017/HowToCook",
    "lang": "Shell"
  },
  {
    "title": "readysettech/readyset",
    "url": "https://github.com/readysettech/readyset",
    "lang": "Rust"
  },
  {
    "title": "LunarVim/nvim-basic-ide",
    "url": "https://github.com/LunarVim/nvim-basic-ide",
    "lang": "Lua"
  },
  {
    "title": "jfecher/ante",
    "url": "https://github.com/jfecher/ante",
    "lang": "Rust"
  },
  {
    "title": "wdzeng/bot-automation",
    "url": "https://github.com/wdzeng/bot-automation"
  },
  {
    "title": "girliemac/a-picture-is-worth-a-1000-words",
    "url": "https://github.com/girliemac/a-picture-is-worth-a-1000-words"
  },
  {
    "title": "neovim/neovim",
    "url": "https://github.com/neovim/neovim",
    "lang": "Vimscript"
  },
  {
    "title": "bitcoin/bitcoin",
    "url": "https://github.com/bitcoin/bitcoin",
    "lang": "C++"
  },
  {
    "title": "topjohnwu/Magisk",
    "url": "https://github.com/topjohnwu/Magisk",
    "lang": "C++"
  },
  {
    "title": "runelite/runelite",
    "url": "https://github.com/runelite/runelite",
    "lang": "Java"
  },
  {
    "title": "Asabeneh/30-Days-Of-JavaScript",
    "url": "https://github.com/Asabeneh/30-Days-Of-JavaScript",
    "lang": "JavaScript"
  },
  {
    "title": "Grasscutters/Grasscutter",
    "url": "https://github.com/Grasscutters/Grasscutter",
    "lang": "Java"
  },
  {
    "title": "Elfocrash/.NET-Backend-Developer-Roadmap",
    "url": "https://github.com/Elfocrash/.NET-Backend-Developer-Roadmap"
  },
  {
    "title": "ventoy/Ventoy",
    "url": "https://github.com/ventoy/Ventoy",
    "lang": "C"
  },
  {
    "title": "donnemartin/system-design-primer",
    "url": "https://github.com/donnemartin/system-design-primer",
    "lang": "Python"
  },
  {
    "title": "python-telegram-bot/python-telegram-bot",
    "url": "https://github.com/python-telegram-bot/python-telegram-bot",
    "lang": "Python"
  },
  {
    "title": "bevyengine/bevy",
    "url": "https://github.com/bevyengine/bevy",
    "lang": "Rust"
  },
  {
    "title": "coderQuad/New-Grad-Positions-2023",
    "url": "https://github.com/coderQuad/New-Grad-Positions-2023"
  },
  {
    "title": "v2fly/v2ray-core",
    "url": "https://github.com/v2fly/v2ray-core",
    "lang": "Go"
  }
]