[
  {
    "title": "WhaleFell/SMSBoom",
    "url": "https://github.com/WhaleFell/SMSBoom",
    "lang": "Python"
  },
  {
    "title": "searxng/searxng",
    "url": "https://github.com/searxng/searxng",
    "lang": "Python"
  },
  {
    "title": "TheAlgorithms/Python",
    "url": "https://github.com/TheAlgorithms/Python",
    "lang": "Python"
  },
  {
    "title": "mtdvio/every-programmer-should-know",
    "url": "https://github.com/mtdvio/every-programmer-should-know"
  },
  {
    "title": "webhdx/PicoBoot",
    "url": "https://github.com/webhdx/PicoBoot",
    "lang": "Python"
  },
  {
    "title": "soimort/you-get",
    "url": "https://github.com/soimort/you-get",
    "lang": "Python"
  },
  {
    "title": "t3-oss/create-t3-app",
    "url": "https://github.com/t3-oss/create-t3-app",
    "lang": "TypeScript"
  },
  {
    "title": "jaywcjlove/awesome-mac",
    "url": "https://github.com/jaywcjlove/awesome-mac",
    "lang": "JavaScript"
  },
  {
    "title": "searxng/searxng-docker",
    "url": "https://github.com/searxng/searxng-docker",
    "lang": "Shell"
  },
  {
    "title": "sherlock-project/sherlock",
    "url": "https://github.com/sherlock-project/sherlock",
    "lang": "Python"
  },
  {
    "title": "chatwoot/chatwoot",
    "url": "https://github.com/chatwoot/chatwoot",
    "lang": "Ruby"
  },
  {
    "title": "solidjs/solid",
    "url": "https://github.com/solidjs/solid",
    "lang": "TypeScript"
  },
  {
    "title": "kwea123/ngp_pl",
    "url": "https://github.com/kwea123/ngp_pl",
    "lang": "JupyterNotebook"
  },
  {
    "title": "LearningOS/rust-based-os-comp2022",
    "url": "https://github.com/LearningOS/rust-based-os-comp2022",
    "lang": "Rust"
  },
  {
    "title": "30-seconds/30-seconds-of-code",
    "url": "https://github.com/30-seconds/30-seconds-of-code",
    "lang": "JavaScript"
  },
  {
    "title": "SerenityOS/serenity",
    "url": "https://github.com/SerenityOS/serenity",
    "lang": "C++"
  },
  {
    "title": "codecrafters-io/build-your-own-x",
    "url": "https://github.com/codecrafters-io/build-your-own-x"
  },
  {
    "title": "Megvii-BaseDetection/YOLOX",
    "url": "https://github.com/Megvii-BaseDetection/YOLOX",
    "lang": "Python"
  },
  {
    "title": "4ian/GDevelop",
    "url": "https://github.com/4ian/GDevelop",
    "lang": "JavaScript"
  },
  {
    "title": "eugenp/tutorials",
    "url": "https://github.com/eugenp/tutorials",
    "lang": "Java"
  },
  {
    "title": "torvalds/linux",
    "url": "https://github.com/torvalds/linux",
    "lang": "C"
  },
  {
    "title": "catchorg/Catch2",
    "url": "https://github.com/catchorg/Catch2",
    "lang": "C++"
  },
  {
    "title": "nvm-sh/nvm",
    "url": "https://github.com/nvm-sh/nvm",
    "lang": "Shell"
  },
  {
    "title": "babysor/MockingBird",
    "url": "https://github.com/babysor/MockingBird",
    "lang": "Python"
  },
  {
    "title": "qianguyihao/Web",
    "url": "https://github.com/qianguyihao/Web"
  }
]