[
  {
    "title": "PowerShell/PowerShell",
    "url": "https://github.com/PowerShell/PowerShell",
    "lang": "C#"
  },
  {
    "title": "ruanyf/weekly",
    "url": "https://github.com/ruanyf/weekly"
  },
  {
    "title": "angular/angular",
    "url": "https://github.com/angular/angular",
    "lang": "TypeScript"
  },
  {
    "title": "mastodon/mastodon",
    "url": "https://github.com/mastodon/mastodon",
    "lang": "Ruby"
  },
  {
    "title": "spacedriveapp/spacedrive",
    "url": "https://github.com/spacedriveapp/spacedrive",
    "lang": "TypeScript"
  },
  {
    "title": "ml-tooling/best-of-ml-python",
    "url": "https://github.com/ml-tooling/best-of-ml-python",
    "lang": "Python"
  },
  {
    "title": "jsonhero-io/jsonhero-web",
    "url": "https://github.com/jsonhero-io/jsonhero-web",
    "lang": "TypeScript"
  },
  {
    "title": "gradio-app/gradio",
    "url": "https://github.com/gradio-app/gradio",
    "lang": "Python"
  },
  {
    "title": "appsmithorg/appsmith",
    "url": "https://github.com/appsmithorg/appsmith",
    "lang": "TypeScript"
  },
  {
    "title": "google/wireit",
    "url": "https://github.com/google/wireit",
    "lang": "TypeScript"
  },
  {
    "title": "naver/fe-news",
    "url": "https://github.com/naver/fe-news"
  },
  {
    "title": "Trainguy9512/trainguys-animation-overhaul",
    "url": "https://github.com/Trainguy9512/trainguys-animation-overhaul",
    "lang": "Java"
  },
  {
    "title": "The-Run-Philosophy-Organization/run",
    "url": "https://github.com/The-Run-Philosophy-Organization/run"
  },
  {
    "title": "neonbjb/tortoise-tts",
    "url": "https://github.com/neonbjb/tortoise-tts",
    "lang": "Python"
  },
  {
    "title": "F5OEO/rpitx",
    "url": "https://github.com/F5OEO/rpitx",
    "lang": "C"
  },
  {
    "title": "hlorus/CAD_Sketcher",
    "url": "https://github.com/hlorus/CAD_Sketcher",
    "lang": "Python"
  },
  {
    "title": "why20021008/hand-write",
    "url": "https://github.com/why20021008/hand-write",
    "lang": "Python"
  },
  {
    "title": "rejetto/hfs",
    "url": "https://github.com/rejetto/hfs",
    "lang": "TypeScript"
  },
  {
    "title": "rancher/rancher",
    "url": "https://github.com/rancher/rancher",
    "lang": "Go"
  },
  {
    "title": "jwasham/coding-interview-university",
    "url": "https://github.com/jwasham/coding-interview-university"
  },
  {
    "title": "ruilisi/fortune-sheet",
    "url": "https://github.com/ruilisi/fortune-sheet",
    "lang": "TypeScript"
  },
  {
    "title": "RedisInsight/RedisInsight",
    "url": "https://github.com/RedisInsight/RedisInsight",
    "lang": "TypeScript"
  },
  {
    "title": "terraform-aws-modules/terraform-aws-eks",
    "url": "https://github.com/terraform-aws-modules/terraform-aws-eks",
    "lang": "HCL"
  },
  {
    "title": "FrancescoXX/free-Web3-resources",
    "url": "https://github.com/FrancescoXX/free-Web3-resources",
    "lang": "HTML"
  },
  {
    "title": "Dec0ne/KrbRelayUp",
    "url": "https://github.com/Dec0ne/KrbRelayUp",
    "lang": "C#"
  }
]